extractCMRRPhysio/__init__.py
extractCMRRPhysio/main.py
extractCMRRPhysio/unwrapper.py
extractCMRRPhysio/version.py
extractCMRRPhysio-1.2.20200020.dist-info/LICENSE
extractCMRRPhysio-1.2.20200020.dist-info/METADATA
extractCMRRPhysio-1.2.20200020.dist-info/WHEEL
extractCMRRPhysio-1.2.20200020.dist-info/entry_points.txt
extractCMRRPhysio-1.2.20200020.dist-info/top_level.txt
extractCMRRPhysio-1.2.20200020.dist-info/zip-safe
extractCMRRPhysio-1.2.20200020.dist-info/RECORD
