Metadata-Version: 2.1
Name: extractCMRRPhysio
Version: 1.2.20200020
Summary: extractCMRRPhysio.m(https://github.com/CMRR-C2P/MB/blob/master/extractCMRRPhysio.m) in Python
Home-page: https://github.com/yinglilu/extractCMRRPhysio_github_actions
Author: YingLi Lu
Author-email: yinglilu@gmail.com
License: MIT
Platform: UNKNOWN
Requires-Python: >=3.6
Requires-Dist: pytest
Requires-Dist: pydicom
